cpkmetrics/__init__.py
cpkmetrics/process_capability.py
cpkmetrics/utils/__init__.py
cpkmetrics/utils/tableprinter.py
cpkmetrics-0.1.0.dist-info/licenses/LICENSE
cpkmetrics-0.1.0.dist-info/METADATA
cpkmetrics-0.1.0.dist-info/WHEEL
cpkmetrics-0.1.0.dist-info/top_level.txt
cpkmetrics-0.1.0.dist-info/RECORD
