Metadata-Version: 2.4
Name: cpkmetrics
Version: 0.1.0
Summary: A featherweight library to compute process capability metrics
Author: Roshan M.
License-Expression: Apache-2.0
Keywords: process capability,cpk,six sigma,statistics
Classifier: Programming Language :: Python :: 3
Classifier: Operating System :: OS Independent
Classifier: Development Status :: 3 - Alpha
Classifier: Intended Audience :: Developers
Classifier: Intended Audience :: Science/Research
Classifier: Intended Audience :: Manufacturing
Classifier: Topic :: Scientific/Engineering
Requires-Python: >=3.10
License-File: LICENSE
Dynamic: license-file
